README.rst
setup.py
sortpythonmethods/__init__.py
sortpythonmethods.egg-info/PKG-INFO
sortpythonmethods.egg-info/SOURCES.txt
sortpythonmethods.egg-info/dependency_links.txt
sortpythonmethods.egg-info/entry_points.txt
sortpythonmethods.egg-info/requires.txt
sortpythonmethods.egg-info/top_level.txt
sortpythonmethods.egg-info/zip-safe