Metadata-Version: 1.1
Name: sortpythonmethods
Version: 47
Summary: Sort methods, imports and classes in a python source file
Home-page: https://github.com/erikdejonge/sortpythonmethod
Author: Erik de Jonge
Author-email: erik@a8.nl
License: GPL
Platform: UNKNOWN
Classifier: Programming Language :: Python :: 3
Classifier: Development Status :: 4 - Beta 
Classifier: Intended Audience :: Developers
Classifier: License :: OSI Approved :: GNU Library or Lesser General Public License (LGPL)
Classifier: Operating System :: POSIX
Classifier: Topic :: Software Development :: Libraries :: Python Modules
Classifier: Topic :: Software Development :: Testing
Classifier: Topic :: System
